MANIFEST.in
README.rst
setup.cfg
setup.py
src/Millet.egg-info/PKG-INFO
src/Millet.egg-info/SOURCES.txt
src/Millet.egg-info/dependency_links.txt
src/Millet.egg-info/requires.txt
src/Millet.egg-info/top_level.txt
src/millet/__init__.py
src/millet/agent.py
src/millet/context.py
src/millet/skill.py
src/millet/timeouts.py
tests/conftest.py
tests/test_agent.py
tests/test_context.py
tests/test_skill.py
tests/test_timeouts.py
tests/.pytest_cache/.gitignore
tests/.pytest_cache/CACHEDIR.TAG
tests/.pytest_cache/README.md
tests/.pytest_cache/v/cache/nodeids
tests/.pytest_cache/v/cache/stepwise
tests/__pycache__/conftest.cpython-39-pytest-6.2.3.pyc
tests/__pycache__/test_agent.cpython-39-pytest-6.2.3.pyc
tests/__pycache__/test_context.cpython-39-pytest-6.2.3.pyc
tests/__pycache__/test_skill.cpython-39-pytest-6.2.3.pyc
tests/__pycache__/test_timeouts.cpython-39-pytest-6.2.3.pyc