Metadata-Version: 2.1
Name: Millet
Version: 2.0.0
Summary: A simple framework for building complex dialogue systems.
Home-page: UNKNOWN
Author: Vyacheslav Rusov
Author-email: odryfox@gmail.com
License: BSD-3-Clause
Project-URL: Code, https://github.com/odryfox/millet
Project-URL: Issue tracker, https://github.com/odryfox/millet/issues
Platform: UNKNOWN
Provides-Extra: dev
Provides-Extra: docs
